LICENSE
README.md
setup.cfg
setup.py
ovrolwasolar/__init__.py
ovrolwasolar/calibration.py
ovrolwasolar/deconvolve.py
ovrolwasolar/file_handler.py
ovrolwasolar/flagging.py
ovrolwasolar/flux_scaling.py
ovrolwasolar/generate_calibrator_model.py
ovrolwasolar/primary_beam.py
ovrolwasolar/refraction_correction.py
ovrolwasolar/selfcal.py
ovrolwasolar/solar_pipeline.py
ovrolwasolar/source_subtraction.py
ovrolwasolar/utils.py
ovrolwasolar/uv_sourcemodel.py
ovrolwasolar/visualization.py
ovrolwasolar.egg-info/PKG-INFO
ovrolwasolar.egg-info/SOURCES.txt
ovrolwasolar.egg-info/dependency_links.txt
ovrolwasolar.egg-info/requires.txt
ovrolwasolar.egg-info/top_level.txt
tests/test_calibrator_model.py
tests/test_file_handler.py
tests/test_flux_scaling_class1.py
tests/test_image_ms_quick.py
tests/test_primary_beam.py
tests/test_primary_beam_nivedita_beam.py
tests/test_woody_beam.py