Metadata-Version: 2.1
Name: ovrolwasolar
Version: 0.1.1
Summary: Calibration, imaging, and analysis of solar data taken by the Owens Valley Long Wavelength Array (OVRO-LWA)
Home-page: https://github.com/ovro-eovsa/ovro-lwa-solar
Author: Bin Chen, Surajit Mondal, Peijin Zhang
Author-email: bin.chen@njit.edu
Classifier: Programming Language :: Python :: 3
Classifier: License :: OSI Approved :: MIT License
Classifier: Operating System :: OS Independent
Requires-Python: >=3.8
License-File: LICENSE
